crema/__init__.py
crema/analyze.py
crema/exceptions.py
crema/layers.py
crema/utils.py
crema/version.py
crema/models/__init__.py
crema/models/base.py
crema/models/chord.py
crema/models/chord/model.h5
crema/models/chord/model_spec.pkl
crema/models/chord/muda.pkl
crema/models/chord/pump.pkl
crema/models/chord/test_scores.json
crema/models/chord/version.txt
crema-0.2.0.dist-info/LICENSE.md
crema-0.2.0.dist-info/METADATA
crema-0.2.0.dist-info/WHEEL
crema-0.2.0.dist-info/top_level.txt
crema-0.2.0.dist-info/RECORD
