Metadata-Version: 2.1
Name: crema
Version: 0.2.0
Summary: Convolutional-recurrent estimators for music analysis
Home-page: https://github.com/bmcfee/crema
Download-URL: https://github.com/bmcfee/crema/releases
Author: Brian McFee
License: ISC
Project-URL: Source, https://github.com/bmcfee/crema
Project-URL: Download, https://github.com/bmcfee/crema/releases
Platform: UNKNOWN
Classifier: License :: OSI Approved :: ISC License (ISCL)
Classifier: Programming Language :: Python
Classifier: Development Status :: 3 - Alpha
Classifier: Intended Audience :: Developers
Classifier: Topic :: Software Development
Classifier: Programming Language :: Python :: 3
Classifier: Programming Language :: Python :: 3.6
Classifier: Programming Language :: Python :: 3.7
Classifier: Programming Language :: Python :: 3.8
Classifier: Programming Language :: Python :: 3.9
License-File: LICENSE.md
Requires-Dist: six
Requires-Dist: librosa (>=0.8)
Requires-Dist: jams (>=0.3)
Requires-Dist: scikit-learn (>=0.18)
Requires-Dist: keras (>=2.6)
Requires-Dist: tensorflow (>=2.0)
Requires-Dist: mir-eval (>=0.5)
Requires-Dist: pumpp (>=0.6)
Requires-Dist: h5py (>=2.7)
Provides-Extra: docs
Requires-Dist: numpydoc ; extra == 'docs'
Requires-Dist: sphinx ; extra == 'docs'
Provides-Extra: tests
Requires-Dist: pytest ; extra == 'tests'
Requires-Dist: pytest-cov ; extra == 'tests'
Provides-Extra: training
Requires-Dist: pescador (>=2.0.1) ; extra == 'training'
Requires-Dist: muda ; extra == 'training'
